nslookup/__init__.py
nslookup/nslookup.py
nslookup-1.8.1.dist-info/LICENSE
nslookup-1.8.1.dist-info/METADATA
nslookup-1.8.1.dist-info/WHEEL
nslookup-1.8.1.dist-info/top_level.txt
nslookup-1.8.1.dist-info/zip-safe
nslookup-1.8.1.dist-info/RECORD
