Metadata-Version: 2.1
Name: nslookup
Version: 1.8.1
Summary: Sensible high-level DNS lookups in Python, using DNSpython resolver
Home-page: https://github.com/wesinator/pynslookup
Author: wesinator
License: UNKNOWN
Keywords: dns
Platform: UNKNOWN
Classifier: Intended Audience :: Developers
Classifier: License :: OSI Approved :: Mozilla Public License 2.0 (MPL 2.0)
Classifier: Natural Language :: English
Classifier: Programming Language :: Python :: 3
License-File: LICENSE
Requires-Dist: dnspython
